[
  {
    "first_and_last_name": "George Orwell"
  },
  {
    "first_and_last_name": "Ernest Hemingway"
  },
  {
    "first_and_last_name": "Roald Dahl"
  },
  {
    "first_and_last_name": "Kurt Vonnegut"
  },
  {
    "first_and_last_name": "Stephen King"
  },
  {
    "first_and_last_name": "Suzanne Collins"
  },
  {
    "first_and_last_name": "Dan Brown"
  },
  {
    "first_and_last_name": "Alice Sebold"
  },
  {
    "first_and_last_name": "Andrzej Sapkowski"
  },
  {
    "first_and_last_name": "Olga Tokarczuk"
  }
]
